packaging_experiment.py
mp_packaging_experiment-0.10.dist-info/METADATA
mp_packaging_experiment-0.10.dist-info/WHEEL
mp_packaging_experiment-0.10.dist-info/entry_points.txt
mp_packaging_experiment-0.10.dist-info/top_level.txt
mp_packaging_experiment-0.10.dist-info/RECORD
