Metadata-Version: 2.1
Name: mp-packaging-experiment
Version: 0.10
Summary: Experiment for packaging for MicroPython
Home-page: https://github.com/aivarannamaa/packaging_experiment
Author: Aivar Annamaa
License: MIT
Project-URL: Source code, https://github.com/aivarannamaa/packaging_experiment
Project-URL: Bug tracker, https://github.com/aivarannamaa/packaging_experiment/issues
Keywords: MicroPython CircuitPython pip upip
Platform: Windows
Platform: macOS
Platform: Linux
Platform: MicroPython
Platform: CircuitPython
Classifier: Development Status :: 4 - Beta
Classifier: Environment :: Console
Classifier: Intended Audience :: Developers
Classifier: License :: Freeware
Classifier: License :: OSI Approved :: MIT License
Classifier: Natural Language :: English
Classifier: Operating System :: MacOS
Classifier: Operating System :: Microsoft :: Windows
Classifier: Operating System :: POSIX
Classifier: Operating System :: POSIX :: Linux
Classifier: Programming Language :: Python
Classifier: Programming Language :: Python :: 3
Classifier: Programming Language :: Python :: 3 :: Only
Classifier: Programming Language :: Python :: 3.6
Classifier: Programming Language :: Python :: 3.7
Classifier: Programming Language :: Python :: 3.8
Classifier: Programming Language :: Python :: 3.9
Classifier: Programming Language :: Python :: Implementation :: MicroPython
Classifier: Topic :: Software Development
Requires-Dist: Adafruit-PlatformDetect (>=3.13.0) ; implementation_name == "blah"
